lsreader-0.1.47.data/purelib/lsreader/__init__.py
lsreader-0.1.47.data/purelib/lsreader/lsreader.so
lsreader-0.1.47.dist-info/METADATA
lsreader-0.1.47.dist-info/WHEEL
lsreader-0.1.47.dist-info/top_level.txt
lsreader-0.1.47.dist-info/RECORD
