Metadata-Version: 2.1
Name: lsreader
Version: 0.1.47
Summary: A reader to extract LS-DYNA results
Home-page: UNKNOWN
Author: LS-PrePost
Author-email: xi.he@ansys.com
License: UNKNOWN
Keywords: ls-dyna,d3plot,binout
Platform: UNKNOWN
Classifier: Development Status :: 3 - Alpha
Classifier: Programming Language :: C++
Classifier: Operating System :: Microsoft :: Windows
Classifier: Operating System :: POSIX :: Linux
Classifier: Programming Language :: Python :: 3.6
Classifier: Programming Language :: Python :: 3.7
Classifier: Programming Language :: Python :: 3.8
Requires-Python: >=3.6
Requires-Dist: numpy
